obespoir/__init__.py
obespoir/include_libs.py
obespoir/base/__init__.py
obespoir/base/common_define.py
obespoir/base/data_pack.py
obespoir/base/global_object.py
obespoir/base/ob_handler.py
obespoir/base/ob_protocol.py
obespoir/base/ob_route.py
obespoir/db/__init__.py
obespoir/db/mongo.py
obespoir/httpserver/__init__.py
obespoir/httpserver/handler.py
obespoir/httpserver/route.py
obespoir/obespoir/__init__.py
obespoir/obespoir/include_libs.py
obespoir/obespoir/base/__init__.py
obespoir/obespoir/base/common_define.py
obespoir/obespoir/base/data_pack.py
obespoir/obespoir/base/global_object.py
obespoir/obespoir/base/ob_handler.py
obespoir/obespoir/base/ob_protocol.py
obespoir/obespoir/base/ob_route.py
obespoir/obespoir/db/__init__.py
obespoir/obespoir/db/mongo.py
obespoir/obespoir/httpserver/__init__.py
obespoir/obespoir/httpserver/handler.py
obespoir/obespoir/httpserver/route.py
obespoir/obespoir/obespoir/__init__.py
obespoir/obespoir/obespoir/include_libs.py
obespoir/obespoir/obespoir/base/__init__.py
obespoir/obespoir/obespoir/base/common_define.py
obespoir/obespoir/obespoir/base/data_pack.py
obespoir/obespoir/obespoir/base/global_object.py
obespoir/obespoir/obespoir/base/ob_handler.py
obespoir/obespoir/obespoir/base/ob_protocol.py
obespoir/obespoir/obespoir/base/ob_route.py
obespoir/obespoir/obespoir/db/__init__.py
obespoir/obespoir/obespoir/db/mongo.py
obespoir/obespoir/obespoir/httpserver/__init__.py
obespoir/obespoir/obespoir/httpserver/handler.py
obespoir/obespoir/obespoir/httpserver/route.py
obespoir/obespoir/obespoir/obespoir/__init__.py
obespoir/obespoir/obespoir/obespoir/include_libs.py
obespoir/obespoir/obespoir/obespoir/base/__init__.py
obespoir/obespoir/obespoir/obespoir/base/common_define.py
obespoir/obespoir/obespoir/obespoir/base/data_pack.py
obespoir/obespoir/obespoir/obespoir/base/global_object.py
obespoir/obespoir/obespoir/obespoir/base/ob_handler.py
obespoir/obespoir/obespoir/obespoir/base/ob_protocol.py
obEspoir-0.2.4.dist-info/LICENSE
obEspoir-0.2.4.dist-info/METADATA
obEspoir-0.2.4.dist-info/WHEEL
obEspoir-0.2.4.dist-info/top_level.txt
obEspoir-0.2.4.dist-info/RECORD
