Metadata-Version: 2.1
Name: obEspoir
Version: 0.2.4
Summary: a distribute game frame
Home-page: https://gitee.com/jamon/obEspoir.git
Author: jamon
Author-email: jamonhe@foxmail.com
License: MIT Licence
Keywords: pip,obEspoir,game,server,frame,distribute
Platform: any
Requires-Python: >=3.6
